guestbook/__init__.py
guestbook/templates/index.html
guestbook/static/main.css
guestbook-1.0.0.dist-info/METADATA
guestbook-1.0.0.dist-info/top_level.txt
guestbook-1.0.0.dist-info/WHEEL
guestbook-1.0.0.dist-info/RECORD
guestbook-1.0.0.dist-info/metadata.json
guestbook-1.0.0.dist-info/DESCRIPTION.rst
guestbook-1.0.0.dist-info/entry_points.txt
